carlib/__init__.py
carlib/checkpoints.py
carlib/cli.py
carlib/dataset_to_car.py
carlib/decode.py
carlib/install_helpers.py
carlib/loaders.py
carlib/setup.py
carlib/transforms.py
carlib/configs/README.md
carlib/configs/audio_config.yaml
carlib/configs/image_config.yaml
carlib/configs/r2_config.yaml
carlib/configs/video_config.yaml
carlib/evaluation/__init__.py
carlib/evaluation/analyze_results.py
carlib/evaluation/benchmark.py
carlib/processors/__init__.py
carlib/processors/audio_codecs.py
carlib/processors/image_codecs.py
carlib/processors/memory_utils.py
carlib/processors/utils.py
carlib/processors/video_codecs.py
carlib-1.3.43.dist-info/licenses/LICENSE
carlib-1.3.43.dist-info/METADATA
carlib-1.3.43.dist-info/WHEEL
carlib-1.3.43.dist-info/entry_points.txt
carlib-1.3.43.dist-info/top_level.txt
carlib-1.3.43.dist-info/RECORD
