Metadata-Version: 2.4
Name: carlib
Version: 1.3.43
Summary: Dataset tokenization and CAR format conversion library for efficient neural network training
Author-email: Rightsify <dev@rightsify.com>
Maintainer-email: Rightsify Development Team <dev@rightsify.com>
License: MIT License
Project-URL: Homepage, https://github.com/gcxrightsify/carlib
Project-URL: Bug Reports, https://github.com/gcxrightsify/carlib/issues
Project-URL: Source, https://github.com/gcxrightsify/carlib
Project-URL: Documentation, https://github.com/gcxrightsify/carlib/blob/main/README.md
Project-URL: Repository, https://github.com/gcxrightsify/carlib.git
Project-URL: Changelog, https://github.com/gcxrightsify/carlib/blob/main/CHANGELOG.md
Keywords: machine learning,neural networks,dataset conversion,car format,data preprocessing,audio processing,image processing,video processing,webdataset,hdf5,encodec,compression,benchmarking,evaluation
Classifier: Development Status :: 4 - Beta
Classifier: Intended Audience :: Developers
Classifier: Intended Audience :: Science/Research
Classifier: Intended Audience :: Information Technology
Classifier: License :: OSI Approved :: MIT License
Classifier: Operating System :: OS Independent
Classifier: Operating System :: POSIX :: Linux
Classifier: Operating System :: MacOS :: MacOS X
Classifier: Operating System :: Microsoft :: Windows
Classifier: Programming Language :: Python :: 3
Classifier: Programming Language :: Python :: 3.8
Classifier: Programming Language :: Python :: 3.9
Classifier: Programming Language :: Python :: 3.10
Classifier: Programming Language :: Python :: 3.11
Classifier: Programming Language :: Python :: 3.12
Classifier: Programming Language :: Python :: 3 :: Only
Classifier: Topic :: Scientific/Engineering :: Artificial Intelligence
Classifier: Topic :: Software Development :: Libraries :: Python Modules
Classifier: Topic :: Multimedia :: Sound/Audio
Classifier: Topic :: Multimedia :: Graphics
Classifier: Topic :: Multimedia :: Video
Classifier: Topic :: System :: Archiving :: Compression
Classifier: Topic :: Utilities
Requires-Python: >=3.8
License-File: LICENSE
Requires-Dist: torch>=2.3.0
Requires-Dist: torchaudio>=2.3.0
Requires-Dist: transformers>=4.31.0
Requires-Dist: PyYAML
Requires-Dist: tqdm
Requires-Dist: librosa
Requires-Dist: descript-audio-codec
Requires-Dist: snac
Requires-Dist: opencv-python
Requires-Dist: boto3
Requires-Dist: seaborn
Requires-Dist: pandas
Requires-Dist: webdataset
Requires-Dist: h5py
Requires-Dist: jax
Requires-Dist: grain
Requires-Dist: numpy<2
Requires-Dist: matplotlib
Requires-Dist: soundfile
Dynamic: license-file
